py_nextbus/__init__.py
py_nextbus/client.py
py_nextbus/nextbus.py
py_nextbus/tests.py
py_nextbus-0.1.2.dist-info/METADATA
py_nextbus-0.1.2.dist-info/RECORD
py_nextbus-0.1.2.dist-info/WHEEL
py_nextbus-0.1.2.dist-info/top_level.txt
