Metadata-Version: 2.1
Name: py-nextbus
Version: 0.1.2
Summary: Minimalistic Python client for the NextBus public API for real-time transit arrival data
Home-page: https://github.com/pmaris/py_nextbus
Author: Pierre Maris
License: UNKNOWN
Platform: UNKNOWN
Classifier: Programming Language :: Python :: 3.6 
Classifier: License :: OSI Approved :: MIT License
Classifier: Operating System :: OS Independent
Requires-Python: >=3
